PyPortForward/__init__.py
PyPortForward/__main__.py
PyPortForward/action/__init__.py
PyPortForward/commands/__init__.py
PyPortForward/commands/client.py
PyPortForward/commands/forward.py
PyPortForward/commands/server.py
PyPortForward/commands/setup.py
PyPortForward/database/__init__.py
PyPortForward/database/ODBC/DBLoader.py
PyPortForward/database/ODBC/__init__.py
PyPortForward/database/ODBC/config.py
PyPortForward/database/ODBC/test.py
PyPortForward/network/__init__.py
PyPortForward/network/buffer.py
PyPortForward/network/control.py
PyPortForward/network/transfer.py
PyPortForward/ports/__init__.py
PyPortForward/security/__init__.py
PyPortForward/users/__init__.py
PyPortForward-1.0.0rc2.dist-info/LICENSE
PyPortForward-1.0.0rc2.dist-info/METADATA
PyPortForward-1.0.0rc2.dist-info/WHEEL
PyPortForward-1.0.0rc2.dist-info/entry_points.txt
PyPortForward-1.0.0rc2.dist-info/top_level.txt
PyPortForward-1.0.0rc2.dist-info/RECORD
