Metadata-Version: 2.1
Name: PyPortForward
Version: 1.0.0rc2
Summary: A simple port forward client and manager written in Python
Home-page: https://github.com/onTDB/PyPortForward
Author: onTDB
Author-email: github@ontdb.com
Classifier: Programming Language :: Python :: 3
Classifier: License :: OSI Approved :: MIT License
Classifier: Operating System :: OS Independent
Requires-Python: >=3.5
License-File: LICENSE
Requires-Dist: flask
Requires-Dist: flask-cors
Requires-Dist: prompt-toolkit
Requires-Dist: Cx-Oracle
Requires-Dist: requests
Requires-Dist: pycryptodome
